TEMPy/__init__.py
TEMPy/_version.py
TEMPy/assembly/__init__.py
TEMPy/assembly/assembly.py
TEMPy/assembly/gamma.py
TEMPy/cli/__init__.py
TEMPy/cli/arg_parser.py
TEMPy/cli/class_arg.py
TEMPy/core/__init__.py
TEMPy/core/data/__init__.py
TEMPy/core/data/download.py
TEMPy/core/errors/__init__.py
TEMPy/core/errors/instance.py
TEMPy/graphics/__init__.py
TEMPy/graphics/show_plot.py
TEMPy/map_process/__init__.py
TEMPy/map_process/map_filters.py
TEMPy/map_process/process.py
TEMPy/maps/__init__.py
TEMPy/maps/em_map.py
TEMPy/maps/map_parser.py
TEMPy/maps/map_transform_score.py
TEMPy/math/__init__.py
TEMPy/math/cluster.py
TEMPy/math/consensus.py
TEMPy/math/fourier.py
TEMPy/math/quaternion.py
TEMPy/math/transform_parser.py
TEMPy/math/vector.py
TEMPy/math/vq.py
TEMPy/optimisation/__init__.py
TEMPy/optimisation/ensemble_generation.py
TEMPy/protein/__init__.py
TEMPy/protein/mmcif.py
TEMPy/protein/prot_rep_biopy.py
TEMPy/protein/rigid_body_parser.py
TEMPy/protein/scoring_functions.py
TEMPy/protein/structure_blurrer.py
TEMPy/protein/structure_parser.py
TEMPy/script/__init__.py
TEMPy/script/gamma.py
TEMPy/script/loqfit.py
TEMPy/script/mi.py
TEMPy/script/output.py
TEMPy/script/sccc.py
TEMPy/script/scores.py
TEMPy/script/smoc.py
TEMPy/tempy_data/quaternion_vectors_5000.pk
BioTEMPy-2.1.2.dist-info/METADATA
BioTEMPy-2.1.2.dist-info/WHEEL
BioTEMPy-2.1.2.dist-info/entry_points.txt
BioTEMPy-2.1.2.dist-info/top_level.txt
BioTEMPy-2.1.2.dist-info/RECORD
