Metadata-Version: 2.1
Name: BioTEMPy
Version: 2.1.2
Summary: TEMPy: a Python Library for Assessment of 3D Electron Microscopy Density Fits
Home-page: http://tempy.ismb.lon.ac.uk/
Author: Maya Topf, Daven Vasishtan, Arun Prasad Pandurangan, Irene Farabella, Agnel-Praveen Joseph, Harpal Sahota
Author-email: tempy-help@cryst.bbk.ac.uk
License: UNKNOWN
Platform: UNKNOWN
Classifier: Programming Language :: Python :: 3
Classifier: Operating System :: OS Independent
Classifier: License :: OSI Approved :: GNU General Public License v3 (GPLv3)
Requires-Python: >=3.7
Requires-Dist: biopython ==1.73
Requires-Dist: numpy >=1.16.1
Requires-Dist: scipy >=1.2.0
Requires-Dist: matplotlib
Requires-Dist: gemmi ==0.5.6
Requires-Dist: voxcov >=0.2.6
Requires-Dist: mrcfile
Requires-Dist: pyfftw
